snapai/__init__.py
snapai/logo.py
snapai/utils.py
snapai-0.1.0.dist-info/LICENSE
snapai-0.1.0.dist-info/METADATA
snapai-0.1.0.dist-info/WHEEL
snapai-0.1.0.dist-info/top_level.txt
snapai-0.1.0.dist-info/RECORD
