Metadata-Version: 2.2
Name: snapai
Version: 0.1.0
Summary: A short description of your package
Home-page: https://github.com/dfpipe/snapai
Author: DFpipe
Author-email: Nick Piper <nick.piper@dfpipe.com>
License: MIT License
Project-URL: Homepage, https://github.com/dfpipe/snapai
Project-URL: Repository, https://github.com/dfpipe/snapai
Classifier: Programming Language :: Python :: 3
Classifier: Operating System :: OS Independent
Requires-Python: >=3.6
License-File: LICENSE
Requires-Dist: requests
Requires-Dist: numpy
Requires-Dist: pandas
Dynamic: author
Dynamic: home-page
Dynamic: requires-python
